{
  "id": "migrate-access-system-to-nostr-sdk-system",
  "name": "migrate-access-system-to-nostr-sdk-system",
  "title": "migrate access.System to nostr/sdk.System",
  "description": "",
  "status": "planning",
  "dev_type": null,
  "scope": null,
  "package": null,
  "priority": "P2",
  "creator": "jerry",
  "assignee": "jerry",
  "createdAt": "2026-05-18",
  "completedAt": null,
  "branch": null,
  "base_branch": "main",
  "worktree_path": null,
  "commit": null,
  "pr_url": null,
  "subtasks": [],
  "children": [],
  "parent": null,
  "relatedFiles": [],
  "notes": "",
  "meta": {}
}