{
  "id": "thread-view-with-treeview",
  "name": "thread-view-with-treeview",
  "title": "thread-view-with-treeview",
  "description": "",
  "status": "in_progress",
  "dev_type": null,
  "scope": null,
  "package": null,
  "priority": "P2",
  "creator": "jerry",
  "assignee": "jerry",
  "createdAt": "2026-05-16",
  "completedAt": null,
  "branch": null,
  "base_branch": "main",
  "worktree_path": null,
  "commit": null,
  "pr_url": null,
  "subtasks": [],
  "children": [],
  "parent": null,
  "relatedFiles": [],
  "notes": "",
  "meta": {}
}